alu.v
//`default_nettype none
`timescale 1ns/1ns

// Rutvik Ajit Jere / ECE5545 / rutvikj / Adv VLSI Design Project #1
// Project #1: This code depicts the circuitry of an ALU of a single thread in a warp, 
// in a streamlined multiprocessesor, in a GPU.

module alu(
    clk, rst, in_valid, mask_en, opcode, lane_mask, srcA, srcB,
    use_imm, imm, cmp_signed, sat_mode, pred, warp_id_i, dbg_dryrun,
    alu_out, write_en, Z, N, C, V, out_valid, illegal_opcode, warp_id_o // outputs
);

  input clk, rst, in_valid, mask_en, use_imm;
  input [2:0] opcode;
  input [3:0] lane_mask; // Lanes of the warp 
  input [31:0] srcA, srcB;
  input [7:0] imm;           
  input cmp_signed;     // 1: compute V as signed overflow; 0: V=0
  input sat_mode;       // 1: signed saturating ADD (clamp on overflow)
  input [3:0] pred;     // Per-lane predicate (ANDed with lane_mask)
  input [4:0] warp_id_i;
  input dbg_dryrun;     // 1: test input, won't commit alu_out (write_en=0)

  output wire [31:0] alu_out;
  output reg [3:0] write_en;
  output reg [3:0] Z, N, C, V;
  output reg out_valid;
  output reg illegal_opcode; //opcode = 111
  output reg [4:0] warp_id_o;

  // Initializing everything:
  reg [31:0] R_reg;
  assign alu_out = R_reg;

  wire [3:0] mask_eff = (mask_en ? lane_mask : 4'hF) & pred;
  wire [3:0] commit_mask = dbg_dryrun ? 4'h0 : mask_eff; // commit the output to memory or not

  integer i;
  reg [7:0] a, b, r;
  reg [8:0] sum; // For ADD/SUB operations
  reg       ovf;

  always @(posedge clk) begin
    if (rst) begin
      R_reg <= 32'h0;
      Z <= 4'h0;
      N <= 4'h0;
      C <= 4'h0;
      V <= 4'h0;
      write_en  <= 4'h0;
      out_valid <= 1'b0;
      illegal_opcode<= 1'b0;
      warp_id_o <= 5'd0;
    end else begin
      out_valid  <= 1'b0;
      //illegal_opcode <= 1'b0;

      if (in_valid) begin
        // default flags
        C <= 4'h0;
        V <= 4'h0;

        for (i = 0; i < 4; i = i + 1) begin  // cycle through all the lanes and compute the operation
          a = srcA[i*8 +: 8];
          b = use_imm ? imm : srcB[i*8 +: 8];

          case (opcode)
            3'b000: begin  //ADD
              sum = {1'b0, a} + {1'b0, b};
              r   = sum[7:0];

              // signed overflow
              ovf = (~(a[7]^b[7]) & (r[7]^a[7]));
              V[i] <= cmp_signed ? ovf : 1'b0;

              // unsigned carry
              C[i] <= sum[8];

              // saturate on signed overflow
              if (sat_mode && cmp_signed && ovf) begin
                if (~a[7] && ~b[7]) r = 8'h7F; 
                else                 r = 8'h80;
              end
            end

            3'b001: begin  //SUB 
              sum = {1'b0, a} - {1'b0, b};
              r   = sum[7:0];
              // Borrow
              C[i] <= (a < b);
              
              ovf = ((a[7]^b[7]) & (r[7]^a[7]));
              V[i] <= cmp_signed ? ovf : 1'b0;
            end

            3'b010: r = ~a;        // NOT
            3'b011: r = ~(a & b);  // NAND
            3'b100: r = ~(a | b);  // NOR
            3'b101: r =  (a & b);  // AND
            3'b110: r =  (a | b);  // OR

            default: begin         // 3'b111 -> illegal
              r = 8'h00;
              illegal_opcode <= 1'b1;
            end
          endcase

          // write the final result to the lane
          R_reg[i*8 +: 8] <= r;

          // Basic flags valid for all ops
          Z[i] <= (r == 8'h00);
          N[i] <= r[7];
        end

        write_en  <= commit_mask;
        out_valid <= 1'b1;      
        warp_id_o <= warp_id_i; 
      end
    end
  end

endmodule

//`default_nettype wire

alu_wrapper.v
//`include "alu.v"
`timescale 1ns/1ps

module alu_fsm(
    clk,
    rst,
    start,          // single cycle pulse to start an operation
    wb_ready,       // downstream ready (lets wrapper finish)
    busy,           // high while FSM not in IDLE
    done,           // single cycle pulse when operation completes
    mask_en,
    opcode,
    lane_mask,    
    srcA,         
    srcB,         
    use_imm,
    imm,           
    cmp_signed,
    sat_mode,
    pred,           
    warp_id_i,      
    dbg_dryrun,
    alu_out,        
    write_en,      
    Z, N, C, V,   
    illegal_opcode,
    warp_id_o,     

    // FSM debug
    dbg_alu_out_valid,
    dbg_state     
);

  input clk, rst;
  input start;
  input wb_ready;
  output busy;
  output reg done;
  input mask_en;
  input [2:0] opcode;
  input [3:0] lane_mask;
  input [31:0] srcA, srcB;
  input use_imm;
  input [7:0] imm;
  input cmp_signed;
  input sat_mode;
  input [3:0] pred;
  input [4:0] warp_id_i;
  input dbg_dryrun;
  output [31:0] alu_out;
  output [3:0] write_en;
  output [3:0] Z, N, C, V;
  output illegal_opcode;
  output [4:0] warp_id_o;
  output dbg_alu_out_valid;
  output [5:0] dbg_state;

  reg mask_en_r, use_imm_r, cmp_signed_r, sat_mode_r, dbg_dryrun_r;
  reg [2:0] opcode_r;
  reg [3:0] lane_mask_r, pred_r;
  reg [7:0] imm_r;
  reg [31:0] A_r, B_r;
  reg [4:0] warp_id_r;
  reg [5:0] state, nxt;

  localparam S00_RESET     = 6'd0,
             S01_IDLE      = 6'd1,
             S02_LATCH     = 6'd2,
             S03_DECODE    = 6'd3,
             S04_CHECK_RDY = 6'd4,
             S05_ISSUE     = 6'd5,
             S06_MIC0      = 6'd6,
             S07_MIC1      = 6'd7,
             S08_MIC2      = 6'd8,
             S09_MIC3      = 6'd9,
             S10_MIC4      = 6'd10,
             S11_MIC5      = 6'd11,
             S12_MIC6      = 6'd12,
             S13_MIC7      = 6'd13,
             S14_MIC8      = 6'd14,
             S15_MIC9      = 6'd15,
             S16_MIC10     = 6'd16,
             S17_MIC11     = 6'd17,
             S18_MIC12     = 6'd18,
             S19_MIC13     = 6'd19,
             S20_MIC14     = 6'd20,
             S21_MIC15     = 6'd21,
             S22_MIC16     = 6'd22,
             S23_MIC17     = 6'd23,
             S24_MIC18     = 6'd24,
             S25_MIC19     = 6'd25,
             S26_MIC20     = 6'd26,
             S27_MIC21     = 6'd27,
             S28_MIC22     = 6'd28,
             S29_MIC23     = 6'd29,
             S30_WB_ALIGN  = 6'd30,
             S31_OUT_PULSE = 6'd31,
             S32_COMPLETE  = 6'd32,
             S33_ILLEGAL   = 6'd33,
             S34_SOFTSTALL = 6'd34,
             S35_SPARE     = 6'd35;

  assign dbg_state = state;
  assign busy = (state != S01_IDLE);

  reg  alu_in_valid;  
  wire alu_out_valid;  
  assign dbg_alu_out_valid = alu_out_valid;
  reg  result_seen;  

  alu u_alu(
    .clk        (clk),
    .rst        (rst),
    .in_valid   (alu_in_valid),
    .mask_en    (mask_en_r),
    .opcode         (opcode_r),
    .lane_mask  (lane_mask_r),
    .srcA     (A_r),
    .srcB     (B_r),
    .use_imm    (use_imm_r),
    .imm        (imm_r),
    .cmp_signed (cmp_signed_r),
    .sat_mode   (sat_mode_r),
    .pred       (pred_r),
    .warp_id_i  (warp_id_r),
    .dbg_dryrun (dbg_dryrun_r),

    .alu_out     (alu_out),
    .write_en   (write_en),
    .Z          (Z),
    .N          (N),
    .C          (C),
    .V          (V),
    .out_valid  (alu_out_valid),
    .illegal_opcode (illegal_opcode),
    .warp_id_o  (warp_id_o)
  );

  always @(posedge clk or posedge rst) begin
    if (rst) state <= S00_RESET;
    else     state <= nxt;
  end

  always @* begin
    nxt = state;
    case (state)
      S00_RESET    : nxt = S01_IDLE;
      S01_IDLE     : nxt = (start ? S02_LATCH : S01_IDLE);
      S02_LATCH    : nxt = S03_DECODE;
      S03_DECODE   : nxt = S04_CHECK_RDY;
      S04_CHECK_RDY: nxt = wb_ready ? S05_ISSUE : S04_CHECK_RDY;
      S05_ISSUE    : nxt = S06_MIC0;
      S06_MIC0     : nxt = S07_MIC1;
      S07_MIC1     : nxt = S08_MIC2;
      S08_MIC2     : nxt = S09_MIC3;
      S09_MIC3     : nxt = S10_MIC4;
      S10_MIC4     : nxt = S11_MIC5;
      S11_MIC5     : nxt = S12_MIC6;
      S12_MIC6     : nxt = S13_MIC7;
      S13_MIC7     : nxt = S14_MIC8;
      S14_MIC8     : nxt = S15_MIC9;
      S15_MIC9     : nxt = S16_MIC10;
      S16_MIC10    : nxt = S17_MIC11;
      S17_MIC11    : nxt = S18_MIC12;
      S18_MIC12    : nxt = S19_MIC13;
      S19_MIC13    : nxt = S20_MIC14;
      S20_MIC14    : nxt = S21_MIC15;
      S21_MIC15    : nxt = S22_MIC16;
      S22_MIC16    : nxt = S23_MIC17;
      S23_MIC17    : nxt = S24_MIC18;
      S24_MIC18    : nxt = S25_MIC19;
      S25_MIC19    : nxt = S26_MIC20;
      S26_MIC20    : nxt = S27_MIC21;
      S27_MIC21    : nxt = S28_MIC22;
      S28_MIC22    : nxt = S29_MIC23;
      S29_MIC23    : nxt = S30_WB_ALIGN;
      S30_WB_ALIGN : nxt = (result_seen && wb_ready) ? S31_OUT_PULSE : S30_WB_ALIGN;
      S31_OUT_PULSE: nxt = S32_COMPLETE;
      S32_COMPLETE : nxt = S01_IDLE;
      S33_ILLEGAL  : nxt = S30_WB_ALIGN;
      S34_SOFTSTALL: nxt = S01_IDLE;
      S35_SPARE    : nxt = S01_IDLE;
      default      : nxt = S01_IDLE;
    endcase
  end

  always @(posedge clk or posedge rst) begin
    if (rst) begin
      mask_en_r    <= 1'b0;
      opcode_r     <= 3'b000;
      lane_mask_r  <= 4'h0;
      A_r          <= 32'h0;
      B_r          <= 32'h0;
      use_imm_r    <= 1'b0;
      imm_r        <= 8'h00;
      cmp_signed_r <= 1'b0;
      sat_mode_r   <= 1'b0;
      pred_r       <= 4'hF;  
      warp_id_r    <= 5'd0;
      dbg_dryrun_r <= 1'b0;
      alu_in_valid <= 1'b0;
      result_seen  <= 1'b0;
      done         <= 1'b0;
    end else begin
      alu_in_valid <= 1'b0;
      done         <= 1'b0;

      if (alu_out_valid) result_seen <= 1'b1;
      if (state == S32_COMPLETE) result_seen <= 1'b0;

      case (state)
        S02_LATCH: begin
          mask_en_r    <= mask_en;
          opcode_r     <= opcode;
          lane_mask_r  <= lane_mask;
          A_r          <= srcA;
          B_r          <= srcB;
          use_imm_r    <= use_imm;
          imm_r        <= imm;
          cmp_signed_r <= cmp_signed;
          sat_mode_r   <= sat_mode;
          pred_r       <= pred;
          warp_id_r    <= warp_id_i;
          dbg_dryrun_r <= dbg_dryrun;
        end

        S05_ISSUE: begin
          alu_in_valid <= 1'b1;
        end

        S31_OUT_PULSE: begin
          done <= 1'b1;
        end
      endcase
    end
  end

endmodule

alu_tb.v
`timescale 1ns/1ps
//`include "alu.v"
//`include "alu_wrapper.v"

module tb_alu;

  reg clk = 0;
  always #5 clk = ~clk; // 100 MHz

  reg rst = 1;

  reg  start = 0; 
  reg  wb_ready = 1;  
  wire busy;
  wire done;

  reg mask_en = 1'b1;
  reg [2:0] opcode = 3'b000;
  reg [3:0] lane_mask = 4'hF;  
  reg [31:0] srcA = 32'h0;
  reg [31:0] srcB = 32'h0;
  reg use_imm = 1'b0;
  reg [7:0] imm = 8'h00;
  reg cmp_signed = 1'b1;
  reg sat_mode = 1'b0;
  reg [3:0] pred = 4'hF;  
  reg [4:0] warp_id_i = 5'd7;
  reg dbg_dryrun = 1'b0;

  wire [31:0] alu_out;
  wire [3:0] write_en;
  wire [3:0] Z, N, C, V;
  wire illegal_opcode;
  wire [4:0] warp_id_o;
  wire [5:0] dbg_state;
  wire dbg_alu_out_valid;

  alu_fsm alu_dut (
    .clk(clk), .rst(rst),
    .start(start), .wb_ready(wb_ready), .busy(busy), .done(done),
    .mask_en(mask_en), .opcode(opcode), .lane_mask(lane_mask),
    .srcA(srcA), .srcB(srcB),
    .use_imm(use_imm), .imm(imm), .cmp_signed(cmp_signed), .sat_mode(sat_mode),
    .pred(pred), .warp_id_i(warp_id_i), .dbg_dryrun(dbg_dryrun),

    .alu_out(alu_out), .write_en(write_en),
    .Z(Z), .N(N), .C(C), .V(V),
    .illegal_opcode(illegal_opcode), .warp_id_o(warp_id_o), .dbg_alu_out_valid(dbg_alu_out_valid),
    .dbg_state(dbg_state)
  );

  task pulse_start;
    begin
      @(negedge clk); start <= 1'b1;
      @(negedge clk); start <= 1'b0;
    end
  endtask


  // test sequence
  initial begin
    $dumpfile("simulation_output.vcd");
    $dumpvars(0, tb_alu);

    repeat (4) @(negedge clk);
    rst <= 1'b0;

    // ADD with imm test:
    srcA <= 32'h03_02_01_00;  
    use_imm <= 1'b1;
    imm <= 8'h01;
    opcode <= 3'b000; 
    lane_mask <= 4'hF; pred <= 4'hF;
    wb_ready <= 1'b1;

    wait (!busy); 
    pulse_start();
    wait (done);
    $display("[T1 ADD+imm] alu_out=%h write_en=%b  Z=%b N=%b C=%b V=%b warp_id_o=%0d", alu_out, write_en, Z, N, C, V, warp_id_o);

    // AND with B test:
    use_imm <= 1'b0;
    opcode <= 3'b101;
    srcA <= 32'hF0_F0_F0_F0;
    srcB <= 32'h0F_F0_0F_F0;
    lane_mask <= 4'b1011; 
    pred <= 4'b1110; 

    wait (!busy); 
    pulse_start();
    wait (done);
    $display("[T2 AND    ] alu_out=%h write_en=%b  Z=%b N=%b C=%b V=%b", alu_out, write_en, Z, N, C, V);

    // SUB with imm test:
    opcode <= 3'b001; 
    use_imm <= 1'b1;
    imm <= 8'h01;
    cmp_signed <= 1'b1;
    sat_mode <= 1'b0;
    srcA <= 32'h80_00_7F_01;
    wb_ready <= 1'b0;
    wait (!busy); 
    pulse_start();
    repeat (8) @(negedge clk); 
    wb_ready <= 1'b1; 
    wait (done);
    $display("[T3 SUB-1 ] alu_out=%h write_en=%b  Z=%b N=%b C=%b V=%b", alu_out, write_en, Z, N, C, V);

    // illegal opcode test:
    opcode <= 3'b111;
    use_imm <= 1'b0;
    lane_mask <= 4'hF; pred <= 4'hF;
    srcA <= 32'h12_34_56_78;
    srcB <= 32'hAA_BB_CC_DD;

    wait (!busy); 
    pulse_start();
    wait (done);
    $display("[T4 ILLEGAL] alu_out=%h write_en=%b illegal=%b", alu_out, write_en, illegal_opcode);

    $display("All tests done.");
    #20 $finish;
  end

endmodule

alu.vcd
$date
	Fri Sep 19 22:00:15 2025
$end
$version
	Icarus Verilog
$end
$timescale
	1ps
$end
$scope module tb_alu $end
$var wire 4 ! write_en [3:0] $end
$var wire 5 " warp_id_o [4:0] $end
$var wire 1 # illegal_opcode $end
$var wire 1 $ done $end
$var wire 6 % dbg_state [5:0] $end
$var wire 1 & dbg_alu_out_valid $end
$var wire 1 ' busy $end
$var wire 32 ( alu_out [31:0] $end
$var wire 4 ) Z [3:0] $end
$var wire 4 * V [3:0] $end
$var wire 4 + N [3:0] $end
$var wire 4 , C [3:0] $end
$var reg 1 - clk $end
$var reg 1 . cmp_signed $end
$var reg 1 / dbg_dryrun $end
$var reg 8 0 imm [7:0] $end
$var reg 4 1 lane_mask [3:0] $end
$var reg 1 2 mask_en $end
$var reg 3 3 opcode [2:0] $end
$var reg 4 4 pred [3:0] $end
$var reg 1 5 rst $end
$var reg 1 6 sat_mode $end
$var reg 32 7 srcA [31:0] $end
$var reg 32 8 srcB [31:0] $end
$var reg 1 9 start $end
$var reg 1 : use_imm $end
$var reg 5 ; warp_id_i [4:0] $end
$var reg 1 < wb_ready $end
$scope module alu_dut $end
$var wire 1 - clk $end
$var wire 1 . cmp_signed $end
$var wire 1 & dbg_alu_out_valid $end
$var wire 1 / dbg_dryrun $end
$var wire 6 = dbg_state [5:0] $end
$var wire 8 > imm [7:0] $end
$var wire 4 ? lane_mask [3:0] $end
$var wire 1 2 mask_en $end
$var wire 3 @ opcode [2:0] $end
$var wire 4 A pred [3:0] $end
$var wire 1 5 rst $end
$var wire 1 6 sat_mode $end
$var wire 32 B srcA [31:0] $end
$var wire 32 C srcB [31:0] $end
$var wire 1 9 start $end
$var wire 1 : use_imm $end
$var wire 5 D warp_id_i [4:0] $end
$var wire 1 < wb_ready $end
$var wire 4 E write_en [3:0] $end
$var wire 5 F warp_id_o [4:0] $end
$var wire 1 # illegal_opcode $end
$var wire 1 ' busy $end
$var wire 1 G alu_out_valid $end
$var wire 32 H alu_out [31:0] $end
$var wire 4 I Z [3:0] $end
$var wire 4 J V [3:0] $end
$var wire 4 K N [3:0] $end
$var wire 4 L C [3:0] $end
$var parameter 6 M S00_RESET $end
$var parameter 6 N S01_IDLE $end
$var parameter 6 O S02_LATCH $end
$var parameter 6 P S03_DECODE $end
$var parameter 6 Q S04_CHECK_RDY $end
$var parameter 6 R S05_ISSUE $end
$var parameter 6 S S06_MIC0 $end
$var parameter 6 T S07_MIC1 $end
$var parameter 6 U S08_MIC2 $end
$var parameter 6 V S09_MIC3 $end
$var parameter 6 W S10_MIC4 $end
$var parameter 6 X S11_MIC5 $end
$var parameter 6 Y S12_MIC6 $end
$var parameter 6 Z S13_MIC7 $end
$var parameter 6 [ S14_MIC8 $end
$var parameter 6 \ S15_MIC9 $end
$var parameter 6 ] S16_MIC10 $end
$var parameter 6 ^ S17_MIC11 $end
$var parameter 6 _ S18_MIC12 $end
$var parameter 6 ` S19_MIC13 $end
$var parameter 6 a S20_MIC14 $end
$var parameter 6 b S21_MIC15 $end
$var parameter 6 c S22_MIC16 $end
$var parameter 6 d S23_MIC17 $end
$var parameter 6 e S24_MIC18 $end
$var parameter 6 f S25_MIC19 $end
$var parameter 6 g S26_MIC20 $end
$var parameter 6 h S27_MIC21 $end
$var parameter 6 i S28_MIC22 $end
$var parameter 6 j S29_MIC23 $end
$var parameter 6 k S30_WB_ALIGN $end
$var parameter 6 l S31_OUT_PULSE $end
$var parameter 6 m S32_COMPLETE $end
$var parameter 6 n S33_ILLEGAL $end
$var parameter 6 o S34_SOFTSTALL $end
$var parameter 6 p S35_SPARE $end
$var reg 32 q A_r [31:0] $end
$var reg 32 r B_r [31:0] $end
$var reg 1 s alu_in_valid $end
$var reg 1 t cmp_signed_r $end
$var reg 1 u dbg_dryrun_r $end
$var reg 1 $ done $end
$var reg 8 v imm_r [7:0] $end
$var reg 4 w lane_mask_r [3:0] $end
$var reg 1 x mask_en_r $end
$var reg 6 y nxt [5:0] $end
$var reg 3 z opcode_r [2:0] $end
$var reg 4 { pred_r [3:0] $end
$var reg 1 | result_seen $end
$var reg 1 } sat_mode_r $end
$var reg 6 ~ state [5:0] $end
$var reg 1 !" use_imm_r $end
$var reg 5 "" warp_id_r [4:0] $end
$scope module u_alu $end
$var wire 32 #" alu_out [31:0] $end
$var wire 1 - clk $end
$var wire 1 t cmp_signed $end
$var wire 1 u dbg_dryrun $end
$var wire 8 $" imm [7:0] $end
$var wire 1 s in_valid $end
$var wire 4 %" lane_mask [3:0] $end
$var wire 4 &" mask_eff [3:0] $end
$var wire 1 x mask_en $end
$var wire 3 '" opcode [2:0] $end
$var wire 4 (" pred [3:0] $end
$var wire 1 5 rst $end
$var wire 1 } sat_mode $end
$var wire 32 )" srcA [31:0] $end
$var wire 32 *" srcB [31:0] $end
$var wire 1 !" use_imm $end
$var wire 5 +" warp_id_i [4:0] $end
$var wire 4 ," commit_mask [3:0] $end
$var reg 4 -" C [3:0] $end
$var reg 4 ." N [3:0] $end
$var reg 32 /" R_reg [31:0] $end
$var reg 4 0" V [3:0] $end
$var reg 4 1" Z [3:0] $end
$var reg 8 2" a [7:0] $end
$var reg 8 3" b [7:0] $end
$var reg 1 # illegal_opcode $end
$var reg 1 G out_valid $end
$var reg 1 4" ovf $end
$var reg 8 5" r [7:0] $end
$var reg 9 6" sum [8:0] $end
$var reg 5 7" warp_id_o [4:0] $end
$var reg 4 8" write_en [3:0] $end
$var integer 32 9" i [31:0] $end
$upscope $end
$upscope $end
$scope task pulse_start $end
$upscope $end
$upscope $end
$enddefinitions $end
$comment Show the parameter values. $end
$dumpall
b100011 p
b100010 o
b100001 n
b100000 m
b11111 l
b11110 k
b11101 j
b11100 i
b11011 h
b11010 g
b11001 f
b11000 e
b10111 d
b10110 c
b10101 b
b10100 a
b10011 `
b10010 _
b10001 ^
b10000 ]
b1111 \
b1110 [
b1101 Z
b1100 Y
b1011 X
b1010 W
b1001 V
b1000 U
b111 T
b110 S
b101 R
b100 Q
b11 P
b10 O
b1 N
b0 M
$end
#0
$dumpvars
bx 9"
bx 8"
bx 7"
bx 6"
bx 5"
x4"
bx 3"
bx 2"
bx 1"
bx 0"
bx /"
bx ."
bx -"
b1111 ,"
b0 +"
b0 *"
b0 )"
b1111 ("
b0 '"
b1111 &"
b0 %"
b0 $"
bx #"
b0 ""
0!"
b0 ~
0}
0|
b1111 {
b0 z
b1 y
0x
b0 w
b0 v
0u
0t
0s
b0 r
b0 q
bx L
bx K
bx J
bx I
bx H
xG
bx F
bx E
b111 D
b0 C
b0 B
b1111 A
b0 @
b1111 ?
b0 >
b0 =
1<
b111 ;
0:
09
b0 8
b0 7
06
15
b1111 4
b0 3
12
b1111 1
b0 0
0/
1.
0-
bx ,
bx +
bx *
bx )
bx (
1'
x&
b0 %
0$
x#
bx "
bx !
$end
#5000
b0 "
b0 F
b0 7"
0#
0&
0G
b0 !
b0 E
b0 8"
b0 *
b0 J
b0 0"
b0 ,
b0 L
b0 -"
b0 +
b0 K
b0 ."
b0 )
b0 I
b0 1"
b0 (
b0 H
b0 #"
b0 /"
1-
#10000
0-
#15000
1-
#20000
0-
#25000
1-
#30000
0-
#35000
1-
#40000
b1 0
b1 >
1:
b11000000100000000100000000 7
b11000000100000000100000000 B
05
0-
#45000
0'
b1 %
b1 =
b1 ~
1-
#50000
b10 y
19
0-
#55000
b11 y
1'
b10 %
b10 =
b10 ~
1-
#60000
b11 y
09
0-
#65000
b100 y
b111 ""
b111 +"
1t
b1 v
b1 $"
1!"
b11000000100000000100000000 q
b11000000100000000100000000 )"
b1111 w
b1111 %"
1x
b11 %
b11 =
b11 ~
1-
#70000
0-
#75000
b101 y
b100 %
b100 =
b100 ~
1-
#80000
0-
#85000
b110 y
b101 %
b101 =
b101 ~
1-
#90000
0-
#95000
b111 y
b110 %
b110 =
b110 ~
1s
1-
#100000
0-
#105000
b1000 y
b111 "
b111 F
b111 7"
1&
1G
b1111 !
b1111 E
b1111 8"
b100000000110000001000000001 (
b100000000110000001000000001 H
b100000000110000001000000001 #"
b100000000110000001000000001 /"
0s
b111 %
b111 =
b111 ~
04"
b100 5"
b100 6"
b1 3"
b11 2"
b100 9"
1-
#110000
0-
#115000
b1001 y
0&
0G
b1000 %
b1000 =
b1000 ~
1|
1-
#120000
0-
#125000
b1010 y
b1001 %
b1001 =
b1001 ~
1-
#130000
0-
#135000
b1011 y
b1010 %
b1010 =
b1010 ~
1-
#140000
0-
#145000
b1100 y
b1011 %
b1011 =
b1011 ~
1-
#150000
0-
#155000
b1101 y
b1100 %
b1100 =
b1100 ~
1-
#160000
0-
#165000
b1110 y
b1101 %
b1101 =
b1101 ~
1-
#170000
0-
#175000
b1111 y
b1110 %
b1110 =
b1110 ~
1-
#180000
0-
#185000
b10000 y
b1111 %
b1111 =
b1111 ~
1-
#190000
0-
#195000
b10001 y
b10000 %
b10000 =
b10000 ~
1-
#200000
0-
#205000
b10010 y
b10001 %
b10001 =
b10001 ~
1-
#210000
0-
#215000
b10011 y
b10010 %
b10010 =
b10010 ~
1-
#220000
0-
#225000
b10100 y
b10011 %
b10011 =
b10011 ~
1-
#230000
0-
#235000
b10101 y
b10100 %
b10100 =
b10100 ~
1-
#240000
0-
#245000
b10110 y
b10101 %
b10101 =
b10101 ~
1-
#250000
0-
#255000
b10111 y
b10110 %
b10110 =
b10110 ~
1-
#260000
0-
#265000
b11000 y
b10111 %
b10111 =
b10111 ~
1-
#270000
0-
#275000
b11001 y
b11000 %
b11000 =
b11000 ~
1-
#280000
0-
#285000
b11010 y
b11001 %
b11001 =
b11001 ~
1-
#290000
0-
#295000
b11011 y
b11010 %
b11010 =
b11010 ~
1-
#300000
0-
#305000
b11100 y
b11011 %
b11011 =
b11011 ~
1-
#310000
0-
#315000
b11101 y
b11100 %
b11100 =
b11100 ~
1-
#320000
0-
#325000
b11110 y
b11101 %
b11101 =
b11101 ~
1-
#330000
0-
#335000
b11111 y
b11110 %
b11110 =
b11110 ~
1-
#340000
0-
#345000
b100000 y
b11111 %
b11111 =
b11111 ~
1-
#350000
0-
#355000
b1110 4
b1110 A
b1011 1
b1011 ?
b1111111100000000111111110000 8
b1111111100000000111111110000 C
b11110000111100001111000011110000 7
b11110000111100001111000011110000 B
b101 3
b101 @
0:
b1 y
b100000 %
b100000 =
b100000 ~
1$
1-
#360000
0-
#365000
0|
0$
0'
b1 %
b1 =
b1 ~
1-
#370000
b10 y
19
0-
#375000
b11 y
1'
b10 %
b10 =
b10 ~
1-
#380000
b11 y
09
0-
#385000
b1010 ,"
b1010 &"
b100 y
b1110 {
b1110 ("
0!"
b1111111100000000111111110000 r
b1111111100000000111111110000 *"
b11110000111100001111000011110000 q
b11110000111100001111000011110000 )"
b1011 w
b1011 %"
b101 z
b101 '"
b11 %
b11 =
b11 ~
1-
#390000
0-
#395000
b101 y
b100 %
b100 =
b100 ~
1-
#400000
0-
#405000
b110 y
b101 %
b101 =
b101 ~
1-
#410000
0-
#415000
b111 y
b110 %
b110 =
b110 ~
1s
1-
#420000
0-
#425000
b1000 y
1&
1G
b1010 !
b1010 E
b1010 8"
b1010 )
b1010 I
b1010 1"
b101 +
b101 K
b101 ."
b111100000000000011110000 (
b111100000000000011110000 H
b111100000000000011110000 #"
b111100000000000011110000 /"
0s
b111 %
b111 =
b111 ~
b0 5"
b1111 3"
b11110000 2"
b100 9"
1-
#430000
0-
#435000
b1001 y
0&
0G
b1000 %
b1000 =
b1000 ~
1|
1-
#440000
0-
#445000
b1010 y
b1001 %
b1001 =
b1001 ~
1-
#450000
0-
#455000
b1011 y
b1010 %
b1010 =
b1010 ~
1-
#460000
0-
#465000
b1100 y
b1011 %
b1011 =
b1011 ~
1-
#470000
0-
#475000
b1101 y
b1100 %
b1100 =
b1100 ~
1-
#480000
0-
#485000
b1110 y
b1101 %
b1101 =
b1101 ~
1-
#490000
0-
#495000
b1111 y
b1110 %
b1110 =
b1110 ~
1-
#500000
0-
#505000
b10000 y
b1111 %
b1111 =
b1111 ~
1-
#510000
0-
#515000
b10001 y
b10000 %
b10000 =
b10000 ~
1-
#520000
0-
#525000
b10010 y
b10001 %
b10001 =
b10001 ~
1-
#530000
0-
#535000
b10011 y
b10010 %
b10010 =
b10010 ~
1-
#540000
0-
#545000
b10100 y
b10011 %
b10011 =
b10011 ~
1-
#550000
0-
#555000
b10101 y
b10100 %
b10100 =
b10100 ~
1-
#560000
0-
#565000
b10110 y
b10101 %
b10101 =
b10101 ~
1-
#570000
0-
#575000
b10111 y
b10110 %
b10110 =
b10110 ~
1-
#580000
0-
#585000
b11000 y
b10111 %
b10111 =
b10111 ~
1-
#590000
0-
#595000
b11001 y
b11000 %
b11000 =
b11000 ~
1-
#600000
0-
#605000
b11010 y
b11001 %
b11001 =
b11001 ~
1-
#610000
0-
#615000
b11011 y
b11010 %
b11010 =
b11010 ~
1-
#620000
0-
#625000
b11100 y
b11011 %
b11011 =
b11011 ~
1-
#630000
0-
#635000
b11101 y
b11100 %
b11100 =
b11100 ~
1-
#640000
0-
#645000
b11110 y
b11101 %
b11101 =
b11101 ~
1-
#650000
0-
#655000
b11111 y
b11110 %
b11110 =
b11110 ~
1-
#660000
0-
#665000
b100000 y
b11111 %
b11111 =
b11111 ~
1-
#670000
0-
#675000
0<
b10000000000000000111111100000001 7
b10000000000000000111111100000001 B
1:
b1 3
b1 @
b1 y
b100000 %
b100000 =
b100000 ~
1$
1-
#680000
0-
#685000
0|
0$
0'
b1 %
b1 =
b1 ~
1-
#690000
b10 y
19
0-
#695000
b11 y
1'
b10 %
b10 =
b10 ~
1-
#700000
b11 y
09
0-
#705000
b100 y
1!"
b10000000000000000111111100000001 q
b10000000000000000111111100000001 )"
b1 z
b1 '"
b11 %
b11 =
b11 ~
1-
#710000
0-
#715000
b100 %
b100 =
b100 ~
1-
#720000
0-
#725000
1-
#730000
0-
#735000
1-
#740000
0-
#745000
1-
#750000
0-
#755000
1-
#760000
0-
#765000
1-
#770000
0-
#775000
1-
#780000
b101 y
1<
0-
#785000
b110 y
b101 %
b101 =
b101 ~
1-
#790000
0-
#795000
b111 y
b110 %
b110 =
b110 ~
1s
1-
#800000
0-
#805000
b1000 y
1&
1G
b1000 *
b1000 J
b1000 0"
b100 ,
b100 L
b100 -"
b100 +
b100 K
b100 ."
b1 )
b1 I
b1 1"
b1111111111111110111111000000000 (
b1111111111111110111111000000000 H
b1111111111111110111111000000000 #"
b1111111111111110111111000000000 /"
0s
b111 %
b111 =
b111 ~
14"
b1111111 5"
b1111111 6"
b1 3"
b10000000 2"
b100 9"
1-
#810000
0-
#815000
b1001 y
0&
0G
b1000 %
b1000 =
b1000 ~
1|
1-
#820000
0-
#825000
b1010 y
b1001 %
b1001 =
b1001 ~
1-
#830000
0-
#835000
b1011 y
b1010 %
b1010 =
b1010 ~
1-
#840000
0-
#845000
b1100 y
b1011 %
b1011 =
b1011 ~
1-
#850000
0-
#855000
b1101 y
b1100 %
b1100 =
b1100 ~
1-
#860000
0-
#865000
b1110 y
b1101 %
b1101 =
b1101 ~
1-
#870000
0-
#875000
b1111 y
b1110 %
b1110 =
b1110 ~
1-
#880000
0-
#885000
b10000 y
b1111 %
b1111 =
b1111 ~
1-
#890000
0-
#895000
b10001 y
b10000 %
b10000 =
b10000 ~
1-
#900000
0-
#905000
b10010 y
b10001 %
b10001 =
b10001 ~
1-
#910000
0-
#915000
b10011 y
b10010 %
b10010 =
b10010 ~
1-
#920000
0-
#925000
b10100 y
b10011 %
b10011 =
b10011 ~
1-
#930000
0-
#935000
b10101 y
b10100 %
b10100 =
b10100 ~
1-
#940000
0-
#945000
b10110 y
b10101 %
b10101 =
b10101 ~
1-
#950000
0-
#955000
b10111 y
b10110 %
b10110 =
b10110 ~
1-
#960000
0-
#965000
b11000 y
b10111 %
b10111 =
b10111 ~
1-
#970000
0-
#975000
b11001 y
b11000 %
b11000 =
b11000 ~
1-
